{"sections":{"new-page":{"type":"new-page","settings":{"layout":"nt_full","cl_bg":"#ffffff","mg":"50px,,20px,","pd":"","mg_mb":"","pd_mb":""}},"163052000577966607":{"type":"rich_text","settings":{"title":"<h1> Premier Copper Products <h1><\/h1>\n<\/h1>","sub_title":"<br> Browse the Premier Copper Products Collection and find the best copper bathtubs, range hoods, kitchen sinks, lighting, and more!","sub_font":"1","style_title":"title_1","ic_tt":"gem","show_clpr":false,"content":"","align":"tc","layout":"container","cl_bg":"","mg":"-50px,,50px,","pd":"","mg_mb":"","pd_mb":""}},"1654042776ab71e480":{"type":"collection-list","blocks":{"1654042776cd0042fe-0":{"type":"collection","settings":{"collection":"premier-copper-product-range-hoods","image":"shopify:\/\/shop_images\/Screen_Shot_2021-09-01_at_3.09.51_PM_540x_14a9f2f6-c414-4a28-a9c1-1cb938f674de.jpg","img_align":"center","title":"Range Hoods"}},"1654042776cd0042fe-1":{"type":"collection","settings":{"collection":"premier-copper-products-bathtubs","image":"shopify:\/\/shop_images\/Screen_Shot_2021-09-01_at_3.09.31_PM_540x_8034133b-5190-447f-87e6-52056f2a18e9.jpg","img_align":"center","title":"Bathtubs"}},"1654042776cd0042fe-2":{"type":"collection","settings":{"collection":"premier-copper-products-kitchen-sinks","image":"shopify:\/\/shop_images\/Screen_Shot_2021-09-01_at_3.32.03_PM_540x_8f7a8371-4906-48d3-8c7d-90bacce58abb.jpg","img_align":"center","title":"Kitchen Sinks"}},"1654042776cd0042fe-3":{"type":"collection","settings":{"collection":"premier-copper-products-bath-faucets","image":"shopify:\/\/shop_images\/Screen_Shot_2021-09-01_at_3.16.37_PM_540x_7e5f2332-fc6a-4566-9cd3-77bb169cc1f7.jpg","img_align":"center","title":"Bath Faucets"}},"8f249268-baea-411e-8494-0c3cd1c3c7ad":{"type":"collection","settings":{"collection":"premier-copper-lighting","image":"shopify:\/\/shop_images\/Screen_Shot_2021-09-01_at_3.50.57_PM_540x_fdd1d3db-b76e-42ba-bf3a-1e9dd1b6495e.jpg","img_align":"center","title":"Lighting"}},"1452a85c-a9a3-4696-b805-cc95b1b05d37":{"type":"collection","settings":{"collection":"premier-copper-products-mirrors","image":"shopify:\/\/shop_images\/Screen_Shot_2021-09-01_at_3.48.58_PM_540x_5cf78ca1-a769-4994-b6d4-12482c7692ad.jpg","img_align":"center","title":"Mirrors"}}},"block_order":["1654042776cd0042fe-0","1654042776cd0042fe-1","1654042776cd0042fe-2","1654042776cd0042fe-3","8f249268-baea-411e-8494-0c3cd1c3c7ad","1452a85c-a9a3-4696-b805-cc95b1b05d37"],"settings":{"title":"SHOP ALL PREMIER COPPER PRODUCTS","sub_title":"","sub_font":"2","style_title":"title_1","ic_tt":"gem","show_clpr":false,"cat_layout":"1","hoverz":true,"cat_design":"7","cat_space":"30","image_ratio":"ratio_nt","col":"4","col_md":"3","col_mb":"6","spn_txt":"Shop now","pr_txt":"products","loop":true,"autoplay":false,"au_time":6,"au_hover":true,"button":false,"btn_vi":"1","btn_owl":"1","btn_color":"0","dot":true,"dot_owl":"1","dot_color":"1","hidden":false,"cp_code":false,"layout":"container","cl_bg":"","mg":"50px,,50px,","pd":"","mg_mb":"","pd_mb":""}},"1650479338c6ac495a":{"type":"featured_collection_owl","settings":{"title":"SHOP ALL PREMIER COPPER PRODUCTS","sub_title":"","sub_font":"2","btn_title":"See all products","style_title":"title_1","ic_tt":"gem","show_clpr":false,"collection":"premier-copper-products","limit":24,"space":30,"use_pagination":"view-all","btn_rd":true,"btn_icon":false,"btn_style":"default","col_pr":"3","col_pr_tb":"3","col_pr_mb":"6","pr_des":"1","show_vendor":false,"use_cdt":false,"round_cd":false,"cdt_des":"1","loop":true,"au_time":0,"au_hover":true,"button":true,"btn_vi":"1","btn_owl":"1","btn_color":"3","dot":true,"dot_owl":"1","dot_color":"1","use_eq_height":false,"image_ratio":"ratio_nt","image_size":"nt_cover","image_position":"8","hidden":false,"cp_code":false,"layout":"container","cl_bg":"","mg":"50px,,50px,","pd":"","mg_mb":"","pd_mb":""}},"1649883624c8d439af":{"type":"rich_text","settings":{"title":"MORE ABOUT PREMIER COPPER PRODUCTS","sub_title":"","sub_font":"2","style_title":"title_1","ic_tt":"gem","show_clpr":false,"content":"<p>Made of 99.7% pure copper, Premier Copper Products is among the top copper kitchen appliance brands in the industry. Premier Copper Products is a family-owned business committed to designing and importing durable, affordable, eco-friendly copper products. Beautifully designed, 100% handcrafted, and refined as your style, you can rest assured your dollar is well spent shopping with Premier Copper Products.<\/p><p>Explore our collection of Premier Copper Products range hoods and sinks for your kitchen and bathtubs and faucets for your bathroom at Rustic Kitchen and Bath. Still on the fence? Check out our review on the brand at our blog <a href=\"https:\/\/www.rustickitchenandbath.com\/a\/blog\/is-premier-copper-a-good-brand\" target=\"_blank\" title=\"https:\/\/www.rustickitchenandbath.com\/a\/blog\/is-premier-copper-a-good-brand\">\"Is Premier Copper a Good Brand\" here.<\/a><\/p>","align":"tc","layout":"container","cl_bg":"","mg":"50px,,50px,","pd":"","mg_mb":"","pd_mb":""}},"16438515603f056744":{"type":"banner","blocks":{"16438515599eaa6821-1":{"type":"image","settings":{"image":"shopify:\/\/shop_images\/Rustic--Affirm--Banners--3000x300_b38d942a-4cb4-4a30-aac8-55e5ea50c375.jpg","img_align":"center","url":"shopify:\/\/pages\/affirm","open_link":"_self","cat_design":"1","title":"","title_2":"","txt_align":"tc","banner_align":"fl_center"}}},"block_order":["16438515599eaa6821-1"],"settings":{"title":"","sub_title":"","sub_font":"2","style_title":"title_1","ic_tt":"gem","show_clpr":false,"cat_space":"30","image_ratio":"auto","col":"12","col_md":"12","col_mb":"12","hoverz":true,"use_shadow":false,"cl_txt":"#ffffff","cl_overlay":"#000000","cl_opacity":0,"layout":"container","cl_bg":"","mg":"50px,,50px,","pd":"","mg_mb":"","pd_mb":""}},"16365845902e216c04":{"type":"feature_columns","blocks":{"16365845902e216c04-0":{"type":"text_block","settings":{"enable_image":true,"image":"shopify:\/\/shop_images\/2_78d5392f-3d04-48b5-b253-5e68209dd0e7.png","title":"Extended Warranties","text":"<p>Choose products you can rely on with our extensive list of product warranties up to 5 years.<\/p>","button_label":"","button_link":"","open_link":"_blank"}},"16365845902e216c04-1":{"type":"text_block","settings":{"enable_image":true,"image":"shopify:\/\/shop_images\/1_973a1c3d-a7c6-475e-b96d-09202d65993c.png","title":"Fast & Free Shipping*","text":"<p>Your order ships next business day for products in stock. Enjoy free shipping on most products!<\/p>","button_label":"","button_link":"","open_link":"_blank"}},"16365845902e216c04-2":{"type":"text_block","settings":{"enable_image":true,"image":"shopify:\/\/shop_images\/3_91feb97d-9830-4e33-8925-27bdceeefaeb.png","title":"Reliable Customer Service","text":"<p>Feel secure about your purchase with our fast, knowledgeable, and reliable customer service team.<\/p>","button_label":"","button_link":"","open_link":"_blank"}}},"block_order":["16365845902e216c04-0","16365845902e216c04-1","16365845902e216c04-2"],"settings":{"title":"WHY RUSTIC KITCHEN AND BATH?","sub_title":"","sub_font":"2","style_title":"title_1","ic_tt":"gem","show_clpr":false,"section_layout":"1","cat_space":"30","col":"4","col_md":"4","col_mb":"12","pos_text":"default","space":20,"align_text":"tc","fs_hd":22,"fs_txt":14,"w_img":0,"loop":true,"au_time":0,"au_hover":true,"button":false,"btn_vi":"1","btn_owl":"1","btn_color":"0","dot":true,"dot_owl":"1","dot_color":"1","layout":"container","cl_bg":"","mg":"50px,,50px,","pd":"","mg_mb":"","pd_mb":""}}},"order":["new-page","163052000577966607","1654042776ab71e480","1650479338c6ac495a","1649883624c8d439af","16438515603f056744","16365845902e216c04"]}