{"sections":{"165047317683b7eb80":{"type":"rich_text","settings":{"title":"<h3>FULGOR MILANO KITCHEN APPLIANCE PACKAGE PROMO<\/h3>","sub_title":"","sub_font":"2","style_title":"title_1","ic_tt":"gem","show_clpr":false,"content":"","align":"tc","layout":"container","cl_bg":"","mg":"50px,,50px,","pd":"","mg_mb":"","pd_mb":""}},"1650473007c5d2c2d9":{"type":"slideshow","blocks":{"1650473006293df698-0":{"type":"img","settings":{"image":"shopify:\/\/shop_images\/Rustic--Fulgor--Milano--Promo--3000x1000.jpg","image_mb":"shopify:\/\/shop_images\/Rustic--Fulgor--Milano--Promo--750x1100.jpg","pos_img":"center center","cl_img":"","link_img1":"shopify:\/\/collections\/fulgor-milano","open_link":"_blank","caption_w":"1","cap_v_pos":50,"cap_h_pos":39,"txt_align":"tl_md","cap_v_pos_mb":50,"cap_h_pos_mb":39,"txt_align_mb":"tl","cl_overlay":"#000000","cl_opacity":0,"ani_img":"none","ani_txt":"none"}}},"block_order":["1650473006293df698-0"],"settings":{"se_height":"adapt","use_custom_h":"1","h_des":"600px","h_tb":"500px","h_mb":"350px","effect":"1","loop":true,"autoplay":false,"au_time":6,"au_hover":true,"button":false,"btn_vi":"1","btn_owl":"1","btn_color":"0","dot":true,"dot_owl":"1","dot_color":"1","layout":"container","cl_bg":"","mg":",,75px,","pd":"","mg_mb":"","pd_mb":""}},"ce8c0735-f06a-4f69-8399-fe8497a4d3fe":{"type":"custom_html","settings":{"code":"<h5>For a limited time, bundle and save on Fulgor Milano appliances. Bundle a select Fulgor Milano cooking appliance (Range, Cooktop, Wall Oven) with a Dishwasher, Range Hood, or Microwave, and take 50% off on the second appliance.<\/h5>\n<h5>Feel free to call our team at <strong><a href=\"tel:18662129706\">1 (866) 212-9706<\/a><\/strong> if you have any questions.<\/h5>","layout":"container","cl_bg":"","mg":"50px,,50px,","pd":"","mg_mb":"","pd_mb":""}},"3ac666ac-da1e-440b-8618-58f31474016b":{"type":"featured_collection_owl","settings":{"title":"CHOOSE THE FIRST HALF OF YOUR BUNDLE","sub_title":"","sub_font":"2","btn_title":"See all products","style_title":"title_1","ic_tt":"gem","show_clpr":false,"collection":"fulgor-milano-cooking-appliance-promo","limit":30,"space":30,"use_pagination":"view-all","btn_rd":true,"btn_icon":false,"btn_style":"default","col_pr":"3","col_pr_tb":"3","col_pr_mb":"6","pr_des":"1","show_vendor":false,"use_cdt":false,"round_cd":false,"cdt_des":"1","loop":true,"au_time":4,"au_hover":true,"button":true,"btn_vi":"1","btn_owl":"1","btn_color":"0","dot":true,"dot_owl":"1","dot_color":"1","use_eq_height":false,"image_ratio":"ratio_nt","image_size":"nt_cover","image_position":"8","hidden":false,"cp_code":false,"layout":"container","cl_bg":"","mg":"75px,,50px,","pd":"","mg_mb":"","pd_mb":""}},"f4f3259b-9db9-42b8-9475-8e232b11f1da":{"type":"tab_collection_owl","blocks":{"template--16016937386166__f4f3259b-9db9-42b8-9475-8e232b11f1da-16795044960f43ffbd-0":{"type":"collection","settings":{"title":"Range Hoods","collection":"fulgor-milano-range-hood-promo","limit":30,"space":30,"use_pagination":"view-all","btn_rd":true,"btn_icon":false,"btn_style":"default","col_pr":"3","col_pr_tb":"3","col_pr_mb":"6","pr_des":"1","show_vendor":false,"use_cdt":false,"round_cd":false,"cdt_des":"1","use_eq_height":false,"image_ratio":"ratio_nt","image_size":"nt_cover","image_position":"8","loop":true,"au_time":4,"au_hover":true,"button":true,"btn_vi":"1","btn_owl":"1","btn_color":"0","dot":true,"dot_owl":"1","dot_color":"1"}},"template--16016937386166__f4f3259b-9db9-42b8-9475-8e232b11f1da-16795044960f43ffbd-1":{"type":"collection","settings":{"title":"Microwaves","collection":"fulgor-milano-microwave-promo","limit":8,"space":30,"use_pagination":"none","btn_rd":true,"btn_icon":false,"btn_style":"default","col_pr":"3","col_pr_tb":"3","col_pr_mb":"6","pr_des":"1","show_vendor":false,"use_cdt":false,"round_cd":false,"cdt_des":"1","use_eq_height":false,"image_ratio":"ratio_nt","image_size":"nt_cover","image_position":"8","loop":true,"au_time":0,"au_hover":true,"button":true,"btn_vi":"1","btn_owl":"1","btn_color":"0","dot":false,"dot_owl":"1","dot_color":"1"}},"template--16016937386166__f4f3259b-9db9-42b8-9475-8e232b11f1da-16795044960f43ffbd-2":{"type":"collection","settings":{"title":"Dishwashers","collection":"fulgor-milano-dishwasher-promo","limit":8,"space":30,"use_pagination":"none","btn_rd":true,"btn_icon":false,"btn_style":"default","col_pr":"3","col_pr_tb":"3","col_pr_mb":"6","pr_des":"1","show_vendor":false,"use_cdt":false,"round_cd":false,"cdt_des":"1","use_eq_height":false,"image_ratio":"ratio_nt","image_size":"nt_cover","image_position":"8","loop":true,"au_time":0,"au_hover":true,"button":true,"btn_vi":"1","btn_owl":"1","btn_color":"0","dot":false,"dot_owl":"1","dot_color":"1"}}},"block_order":["template--16016937386166__f4f3259b-9db9-42b8-9475-8e232b11f1da-16795044960f43ffbd-0","template--16016937386166__f4f3259b-9db9-42b8-9475-8e232b11f1da-16795044960f43ffbd-1","template--16016937386166__f4f3259b-9db9-42b8-9475-8e232b11f1da-16795044960f43ffbd-2"],"settings":{"title":"RECEIVE THE SECOND APPLIANCE 50% OFF","sub_title":"","sub_font":"2","style_title":"title_1","ic_tt":"gem","show_clpr":false,"des_tab":"2","layout":"container","cl_bg":"","mg":"50px,,50px,","pd":"","mg_mb":"","pd_mb":""}}},"order":["165047317683b7eb80","1650473007c5d2c2d9","ce8c0735-f06a-4f69-8399-fe8497a4d3fe","3ac666ac-da1e-440b-8618-58f31474016b","f4f3259b-9db9-42b8-9475-8e232b11f1da"]}